cianparser/__init__.py
cianparser/base_list.py
cianparser/cianparser.py
cianparser/constants.py
cianparser/helpers.py
cianparser/proxy_pool.py
cianparser/url_builder.py
cianparser-1.0.3.dist-info/METADATA
cianparser-1.0.3.dist-info/WHEEL
cianparser-1.0.3.dist-info/top_level.txt
cianparser-1.0.3.dist-info/RECORD
