Metadata-Version: 2.1
Name: cianparser
Version: 1.0.3
Summary: Parser information from Cian website
Home-page: https://github.com/lenarsaitov/cianparser
Author: Lenar Saitov
Author-email: lenarsaitov1@yandex.ru
License: MIT
Keywords: python parser requests cloudscraper beautifulsoup cian realstate
Classifier: Programming Language :: Python :: 3
Classifier: License :: OSI Approved :: MIT License
Classifier: Operating System :: OS Independent
Requires-Dist: cloudscraper
Requires-Dist: beautifulsoup4
Requires-Dist: transliterate
Requires-Dist: lxml
Requires-Dist: datetime
